tvipsconverter/__init__.py
tvipsconverter/__main__.py
tvipsconverter/widget.ui
tvipsconverter/widget_2.ui
tvipsconverter/widgets.py
tvipsconverter/utils/__init__.py
tvipsconverter/utils/blockfile.py
tvipsconverter/utils/hspy.py
tvipsconverter/utils/imagefun.py
tvipsconverter/utils/recorder.py
tvipsconverter/utils/tiffexport.py
tvipsconverter-0.1.3.dist-info/LICENSE
tvipsconverter-0.1.3.dist-info/METADATA
tvipsconverter-0.1.3.dist-info/WHEEL
tvipsconverter-0.1.3.dist-info/entry_points.txt
tvipsconverter-0.1.3.dist-info/top_level.txt
tvipsconverter-0.1.3.dist-info/RECORD
