Metadata-Version: 2.1
Name: tvipsconverter
Version: 0.1.3
Summary: GUI converter for movie data from TVIPS camerasinto other formats like .blo, .tiff and .hspy.Mainly for orientation mapping (PED) or 4D STEM experiments.
Home-page: https://github.com/din14970/TVIPSconverter
Author: Niels Cautaerts, Paddy Harrison
Author-email: nielscautaerts@hotmail.com
License: GPL-3.0
Keywords: TEM
Platform: UNKNOWN
Classifier: Topic :: Scientific/Engineering :: Physics
Classifier: Intended Audience :: Science/Research
Classifier: Operating System :: OS Independent
Classifier: Programming Language :: Python :: 3.8
Requires-Dist: numpy
Requires-Dist: matplotlib
Requires-Dist: scipy (>=1.1.0)
Requires-Dist: tifffile
Requires-Dist: Pillow
Requires-Dist: PyQt5 (>=5.13.2)
Requires-Dist: h5py (>=2.10.0)
Requires-Dist: scikit-image (>=0.17.2)
